tsam/__init__.py
tsam/hyperparametertuning.py
tsam/periodAggregation.py
tsam/representations.py
tsam/timeseriesaggregation.py
tsam/utils/__init__.py
tsam/utils/durationRepresentation.py
tsam/utils/k_maxoids.py
tsam/utils/k_medoids_contiguity.py
tsam/utils/k_medoids_exact.py
tsam/utils/segmentation.py
tsam-2.3.9.dist-info/licenses/LICENSE.txt
tsam-2.3.9.dist-info/METADATA
tsam-2.3.9.dist-info/WHEEL
tsam-2.3.9.dist-info/top_level.txt
tsam-2.3.9.dist-info/RECORD
