Metadata-Version: 2.4
Name: tsam
Version: 2.3.9
Summary: Time series aggregation module (tsam) to create typical periods
Author-email: Leander Kotzur <leander.kotzur@googlemail.com>, Maximilian Hoffmann <maximilian.hoffmann@julumni.fz-juelich.de>
Maintainer-email: Julian Belina <j.belina@fz-juelich.de>
License: ﻿MIT License
Keywords: clustering,optimization
Classifier: Development Status :: 4 - Beta
Classifier: Intended Audience :: End Users/Desktop
Classifier: Intended Audience :: Science/Research
Classifier: License :: OSI Approved :: MIT License
Classifier: Natural Language :: English
Classifier: Operating System :: OS Independent
Classifier: Programming Language :: Python
Classifier: Programming Language :: Python :: 2
Classifier: Programming Language :: Python :: 3
Classifier: Topic :: Scientific/Engineering :: Mathematics
Classifier: Topic :: Software Development :: Libraries :: Python Modules
Requires-Python: <3.14,>=3.9
License-File: LICENSE.txt
Requires-Dist: scikit-learn>=0.0
Requires-Dist: pandas>=2.0.3
Requires-Dist: numpy>=1.20.0
Requires-Dist: pyomo>=6.4.3
Requires-Dist: networkx
Requires-Dist: tqdm
Requires-Dist: highspy
Provides-Extra: dev
Requires-Dist: pytest; extra == "dev"
Requires-Dist: pytest-cov; extra == "dev"
Requires-Dist: codecov; extra == "dev"
Requires-Dist: sphinx; extra == "dev"
Requires-Dist: sphinx-autobuild; extra == "dev"
Requires-Dist: sphinx_book_theme; extra == "dev"
Requires-Dist: twine; extra == "dev"
Dynamic: license-file
